simplegmail/__init__.py
simplegmail/attachment.py
simplegmail/gmail.py
simplegmail/label.py
simplegmail/message.py
simplegmail/query.py
simplegmail-4.1.1.dist-info/LICENSE
simplegmail-4.1.1.dist-info/METADATA
simplegmail-4.1.1.dist-info/WHEEL
simplegmail-4.1.1.dist-info/top_level.txt
simplegmail-4.1.1.dist-info/RECORD
