Metadata-Version: 2.1
Name: simplegmail
Version: 4.1.1
Summary: A simple Python API client for Gmail.
Home-page: https://github.com/jeremyephron/simplegmail
Author: Jeremy Ephron
Author-email: jeremye@cs.stanford.edu
License: UNKNOWN
Platform: UNKNOWN
Classifier: Development Status :: 5 - Production/Stable
Classifier: Programming Language :: Python
Classifier: Programming Language :: Python :: 3
Classifier: Programming Language :: Python :: 3.6
Classifier: License :: OSI Approved :: MIT License
Classifier: Operating System :: OS Independent
